{
  "timestamp": "2025-10-20 16:04:02",
  "iterations": 3,
  "queries": {
    "query_1": {
      "v1_avg_ms": 1098.83,
      "v2_avg_ms": 36.92,
      "improvement_percent": 96.6,
      "speedup_factor": 29.76,
      "v1_min_ms": 1011.01,
      "v1_max_ms": 1182.02,
      "v2_min_ms": 20.95,
      "v2_max_ms": 67.79
    },
    "query_2": {
      "v1_avg_ms": 3253.06,
      "v2_avg_ms": 2925.33,
      "improvement_percent": 10.1,
      "speedup_factor": 1.11,
      "v1_min_ms": 3189.92,
      "v1_max_ms": 3340.01,
      "v2_min_ms": 2747.52,
      "v2_max_ms": 3170.46
    },
    "query_3": {
      "v1_avg_ms": 878.81,
      "v2_avg_ms": 8.16,
      "improvement_percent": 99.1,
      "speedup_factor": 107.65,
      "v1_min_ms": 869.63,
      "v1_max_ms": 893.96,
      "v2_min_ms": 6.54,
      "v2_max_ms": 11.28
    },
    "query_4": {
      "v1_avg_ms": 1101.76,
      "v2_avg_ms": 132.9,
      "improvement_percent": 87.9,
      "speedup_factor": 8.29,
      "v1_min_ms": 1090.72,
      "v1_max_ms": 1113.08,
      "v2_min_ms": 128.5,
      "v2_max_ms": 140.26
    },
    "query_5": {
      "v1_avg_ms": 1419.4,
      "v2_avg_ms": 726.09,
      "improvement_percent": 48.8,
      "speedup_factor": 1.95,
      "v1_min_ms": 1348.68,
      "v1_max_ms": 1520.94,
      "v2_min_ms": 716.89,
      "v2_max_ms": 731.67
    }
  },
  "totals": {
    "total_v1_ms": 7751.86,
    "total_v2_ms": 3829.4,
    "total_improvement_percent": 50.6,
    "total_speedup": 2.02
  }
}